pymarketstack/__init__.py
pymarketstack/downloader.py
pymarketstack/end_of_day.py
pymarketstack/exceptions.py
pymarketstack/helper.py
pymarketstack/query.py
pymarketstack/responses.py
pymarketstack-0.0.7.dist-info/LICENSE
pymarketstack-0.0.7.dist-info/METADATA
pymarketstack-0.0.7.dist-info/WHEEL
pymarketstack-0.0.7.dist-info/top_level.txt
pymarketstack-0.0.7.dist-info/RECORD
