Metadata-Version: 2.1
Name: pymarketstack
Version: 0.0.7
Summary: A python library for the marketstack API
Home-page: https://github.com/NoakPalander/pymarketstack
Author: Noak Palander
Author-email: noak.palander@protonmail.com
Keywords: python,market,stocks,api,marketstack
Classifier: Programming Language :: Python :: 3
Classifier: Operating System :: OS Independent
Classifier: License :: OSI Approved :: Apache Software License
License-File: LICENSE
Requires-Dist: aiohttp
Requires-Dist: marshmallow
Requires-Dist: dataclasses-json
